{
	"info": {
		"_postman_id": "ebe9c385-1a97-46a2-b249-dd60f1bf747a",
		"name": "Votação Desafio",
		"schema": "https://schema.getpostman.com/json/collection/v2.1.0/collection.json",
		"_exporter_id": "37204393"
	},
	"item": [
		{
			"name": "Associado",
			"item": [
				{
					"name": "GET Associado",
					"request": {
						"method": "GET",
						"header": [],
						"url": {
							"raw": "http://localhost:8080/associado",
							"protocol": "http",
							"host": [
								"localhost"
							],
							"port": "8080",
							"path": [
								"associado"
							]
						}
					},
					"response": []
				},
				{
					"name": "Cadastro de Associado",
					"request": {
						"method": "POST",
						"header": [],
						"body": {
							"mode": "raw",
							"raw": "{\r\n    \"cpf\": \"345\"\r\n}",
							"options": {
								"raw": {
									"language": "json"
								}
							}
						},
						"url": {
							"raw": "http://localhost:8080/associado",
							"protocol": "http",
							"host": [
								"localhost"
							],
							"port": "8080",
							"path": [
								"associado"
							]
						}
					},
					"response": []
				},
				{
					"name": "Associado por cpf",
					"request": {
						"method": "GET",
						"header": [],
						"url": {
							"raw": "http://localhost:8080/associado?cpf=123",
							"protocol": "http",
							"host": [
								"localhost"
							],
							"port": "8080",
							"path": [
								"associado"
							],
							"query": [
								{
									"key": "cpf",
									"value": "123"
								}
							]
						}
					},
					"response": []
				}
			]
		},
		{
			"name": "Pauta",
			"item": [
				{
					"name": "GET Pauta",
					"request": {
						"method": "GET",
						"header": [],
						"url": {
							"raw": "http://localhost:8080/pauta",
							"protocol": "http",
							"host": [
								"localhost"
							],
							"port": "8080",
							"path": [
								"pauta"
							]
						}
					},
					"response": []
				},
				{
					"name": "Pauta por Associado id",
					"request": {
						"method": "GET",
						"header": [],
						"url": {
							"raw": "http://localhost:8080/pauta?idAssociado=1",
							"protocol": "http",
							"host": [
								"localhost"
							],
							"port": "8080",
							"path": [
								"pauta"
							],
							"query": [
								{
									"key": "idAssociado",
									"value": "1"
								}
							]
						}
					},
					"response": []
				},
				{
					"name": "Cadastrar Pauta",
					"request": {
						"method": "POST",
						"header": [],
						"body": {
							"mode": "raw",
							"raw": "{\r\n    \"iniciadoEm\": \"2024-07-24T12:41:17.829Z\",\r\n    \"duracao\": \"01:05:00\",\r\n    \"pergunta\": \"Você gosta de cachorros?\",\r\n    \"codigo\": \"MDIyYTUwOWFlOGNi\",\r\n    \"id_associado\": 1\r\n}",
							"options": {
								"raw": {
									"language": "json"
								}
							}
						},
						"url": {
							"raw": "http://localhost:8080/pauta",
							"protocol": "http",
							"host": [
								"localhost"
							],
							"port": "8080",
							"path": [
								"pauta"
							]
						}
					},
					"response": []
				},
				{
					"name": "Pauta por id",
					"request": {
						"method": "GET",
						"header": [],
						"url": {
							"raw": "http://localhost:8080/pauta?id=1",
							"protocol": "http",
							"host": [
								"localhost"
							],
							"port": "8080",
							"path": [
								"pauta"
							],
							"query": [
								{
									"key": "id",
									"value": "1"
								}
							]
						}
					},
					"response": []
				},
				{
					"name": "Pauta por codigo",
					"request": {
						"method": "GET",
						"header": [],
						"url": {
							"raw": "http://localhost:8080/pauta?codigo=MDIyYTUwOWFlOGNi",
							"protocol": "http",
							"host": [
								"localhost"
							],
							"port": "8080",
							"path": [
								"pauta"
							],
							"query": [
								{
									"key": "codigo",
									"value": "MDIyYTUwOWFlOGNi"
								}
							]
						}
					},
					"response": []
				}
			]
		},
		{
			"name": "Votos",
			"item": [
				{
					"name": "Ler Votos",
					"request": {
						"method": "GET",
						"header": [],
						"url": {
							"raw": "http://localhost:8080/votos",
							"protocol": "http",
							"host": [
								"localhost"
							],
							"port": "8080",
							"path": [
								"votos"
							]
						}
					},
					"response": []
				},
				{
					"name": "Votos por Pauta id",
					"request": {
						"method": "GET",
						"header": [],
						"url": {
							"raw": "http://localhost:8080/votos?idPauta=1",
							"protocol": "http",
							"host": [
								"localhost"
							],
							"port": "8080",
							"path": [
								"votos"
							],
							"query": [
								{
									"key": "idPauta",
									"value": "1"
								}
							]
						}
					},
					"response": []
				},
				{
					"name": "Cadastrar votos",
					"request": {
						"method": "POST",
						"header": [],
						"body": {
							"mode": "raw",
							"raw": "{\r\n    \"id_associado\": 2,\r\n    \"id_pauta\": 1,\r\n    \"voto\": \"sim\"\r\n}",
							"options": {
								"raw": {
									"language": "json"
								}
							}
						},
						"url": {
							"raw": "http://localhost:8080/votos",
							"protocol": "http",
							"host": [
								"localhost"
							],
							"port": "8080",
							"path": [
								"votos"
							]
						}
					},
					"response": []
				},
				{
					"name": "Votos por Pauta id e Associado id",
					"request": {
						"method": "GET",
						"header": [],
						"url": {
							"raw": "http://localhost:8080/votos?idPauta=1&idAssociado=2",
							"protocol": "http",
							"host": [
								"localhost"
							],
							"port": "8080",
							"path": [
								"votos"
							],
							"query": [
								{
									"key": "idPauta",
									"value": "1"
								},
								{
									"key": "idAssociado",
									"value": "2"
								}
							]
						}
					},
					"response": []
				}
			]
		}
	]
}