{
  "associado": [
    {
      "cpf": "123",
      "id": 1
    },
    {
      "cpf": "234",
      "id": 2
    },
    {
      "cpf": "345",
      "id": 3
    }
  ],
  "pauta": [
    {
      "iniciadoEm": "2024-07-24T00:38:10.233Z",
      "duracao": "01:00:00",
      "pergunta": "Você gosta de gatos?",
      "codigo": "MDM3ZTZhMDk4YTlm",
      "idAssociado": 1,
      "id": 1
    },
    {
      "iniciadoEm": "2024-07-24T12:41:17.829Z",
      "duracao": "01:05:00",
      "pergunta": "Você gosta de cachorros?",
      "codigo": "MDIyYTUwOWFlOGNi",
      "idAssociado": 1,
      "id": 2
    }
  ],
  "votos": [
    {
      "idAssociado": 1,
      "idPauta": 1,
      "voto": "sim",
      "id": 1
    },
    {
      "idAssociado": 2,
      "idPauta": 1,
      "voto": "nao",
      "id": 2
    },
    {
      "idAssociado": 3,
      "idPauta": 1,
      "voto": "sim",
      "id": 3
    },
    {
      "idAssociado": 1,
      "idPauta": 2,
      "voto": "nao",
      "id": 4
    }
  ]
}